hpc_interact/__init__.py
hpc_interact/hpc_interact.py
hpc_interact-0.1.1.dist-info/LICENSE
hpc_interact-0.1.1.dist-info/METADATA
hpc_interact-0.1.1.dist-info/WHEEL
hpc_interact-0.1.1.dist-info/RECORD
