Metadata-Version: 2.1
Name: hpc-interact
Version: 0.1.1
Summary: Used for file transfer and sending predefined commands to an hpc cluster
Home-page: https://github.com/enviro-lab/hpc-interact.git
License: MIT
Keywords: upload,download,sftp,ssh,expect,file transfer
Author: Sam Kunkleman
Author-email: skunklem@uncc.edu
Requires-Python: >=3.8,<4.0
Classifier: License :: OSI Approved :: MIT License
Classifier: Programming Language :: Python :: 3
Classifier: Programming Language :: Python :: 3.8
Classifier: Programming Language :: Python :: 3.9
Classifier: Programming Language :: Python :: 3.10
Classifier: Programming Language :: Python :: 3.11
Project-URL: Repository, https://github.com/enviro-lab/hpc-interact.git
